GMR_Conv/__init__.py
GMR_Conv/gmr_conv.py
GMR_Conv/gmr_resnet.py
GMR_Conv/gmr_resnet_3d.py
GMR_Conv/gmr_unet.py
GMR_Conv/transforms.py
GMR_Conv/utils.py
gmr_conv-1.0.2.dist-info/licenses/LICENSE
gmr_conv-1.0.2.dist-info/METADATA
gmr_conv-1.0.2.dist-info/WHEEL
gmr_conv-1.0.2.dist-info/top_level.txt
gmr_conv-1.0.2.dist-info/RECORD
