Metadata-Version: 2.4
Name: GMR-Conv
Version: 1.0.2
Summary: Official package for 'GMR-Conv: An Efficient Rotation and Reflection Equivariant Convolution Kernel Using Gaussian Mixture Rings'
Author-email: "Yuexi Du, Jiazhen Zhang, Nicha C. Dvornek, John A. Onofrey" <yuexi.du@yale.edu>
Project-URL: Homepage, https://github.com/XYPB/GMR-Conv
Project-URL: Issue, https://github.com/XYPB/GMR-Conv/issues
Classifier: Programming Language :: Python :: 3
Classifier: License :: OSI Approved :: MIT License
Classifier: Operating System :: OS Independent
Requires-Python: >=3.8
License-File: LICENSE
Requires-Dist: scipy>=1.9.0
Requires-Dist: numpy>=1.22.0
Requires-Dist: torch>=1.8.0
Requires-Dist: pillow>=9.2.0
Requires-Dist: monai>=0.7.0
Dynamic: license-file
